{
  "subjects":
  [
    {
      "id":"1",
      "name":"Chapter 20",
      "notes":
      [
        {
          "id":"1.1",
          "header":"Coulomb's Law",
          "equation":"\\overrightarrow{F_{12}} = \\frac{kq_{1}q_{2}}{r^2}\\hat{r}\\\\\\mbox{Where }\\overrightarrow{F_{12}}\\mbox{ is the force }q_{1}\\mbox{ exerts on }q_{2}\\\\k \\mbox{ is a }\\linkNote{11.2}{constant}\\mbox{.}\\\\\\hat{r}\\mbox{ is the normal of the direction between the charges.}"
        },
        {
          "id":"1.2",
          "header":"Charge Conservation",
          "equation":"\\mbox{The net charge in a closed system is constant.}"
        }
      ]
    }
  ]
}
        
